{
    "year": 1972,
    "original winner": "Nixon",
    "new winner": "McGove.",
    "flipped votes": 3174786,
    "flipped states": {
        "New Mexico": 47262,
        "Wisconsin": 89629,
        "Washington": 134401,
        "California": 563125,
        "Montana": 31890,
        "Oregon": 46964,
        "New York": 620848,
        "Michigan": 251144,
        "New Hampshire": 48645,
        "North Dakota": 36863,
        "Delaware": 24038,
        "Idaho": 59280,
        "Maine": 47938,
        "South Dakota": 13266,
        "Minnesota": 47962,
        "Wyoming": 28054,
        "Illinois": 437354,
        "Connecticut": 127633,
        "Maryland": 161763,
        "Hawaii": 33729,
        "Iowa": 105001,
        "South Carolina": 144579,
        "Alaska": 11192,
        "Vermont": 24488,
        "Rhode Island": 12870,
        "Nevada": 24868
    },
    "total votes": 77744030,
    "percent votes flipped": "4.084%"
}