[
    {
        "year": 1824,
        "original winner": "Adams",
        "new winner": "Jackson",
        "flipped votes": 3176,
        "flipped states": {
            "Ohio": 384,
            "Virginia": 2792
        },
        "total votes": 365928,
        "percent votes flipped": "0.868%"
    },
    {
        "year": 1828,
        "original winner": "Jackson",
        "new winner": "Adams",
        "flipped votes": 12162,
        "flipped states": {
            "Louisiana": 262,
            "Ohio": 2101,
            "Virginia": 7393,
            "Missouri": 2406
        },
        "total votes": 1149216,
        "percent votes flipped": "1.058%"
    },
    {
        "year": 1832,
        "original winner": "Jackson",
        "new winner": "Clay",
        "flipped votes": 14013,
        "flipped states": {
            "Louisiana": 740,
            "New York": 6801,
            "New Jersey": 181,
            "Vermont": 978,
            "Ohio": 2354,
            "New Hampshire": 2959
        },
        "total votes": 1283720,
        "percent votes flipped": "1.092%"
    },
    {
        "year": 1836,
        "original winner": "Van Bu.",
        "new winner": "Harris.",
        "flipped votes": 15935,
        "flipped states": {
            "Michigan": 789,
            "Rhode Island": 128,
            "Pennsylvania": 2112,
            "Maine": 4012,
            "Mississippi": 5149,
            "Illinois": 1575,
            "Connecticut": 248,
            "Louisiana": 1922
        },
        "total votes": 1502811,
        "percent votes flipped": "1.060%"
    },
    {
        "year": 1840,
        "original winner": "Harris.",
        "new winner": "Van Bu.",
        "flipped votes": 8722,
        "flipped states": {
            "Pennsylvania": 168,
            "Delaware": 548,
            "New York": 6635,
            "New Jersey": 1159,
            "Maine": 212
        },
        "total votes": 2412694,
        "percent votes flipped": "0.362%"
    },
    {
        "year": 1844,
        "original winner": "Polk",
        "new winner": "Clay",
        "flipped votes": 2554,
        "flipped states": {
            "New York": 2554
        },
        "total votes": 2703864,
        "percent votes flipped": "0.094%"
    },
    {
        "year": 1848,
        "original winner": "Taylor",
        "new winner": "Cass",
        "flipped votes": 3717,
        "flipped states": {
            "New Jersey": 1558,
            "Georgia": 1374,
            "Delaware": 266,
            "Florida": 519
        },
        "total votes": 2876818,
        "percent votes flipped": "0.129%"
    },
    {
        "year": 1852,
        "original winner": "Pierce",
        "new winner": "Scott",
        "flipped votes": 29586,
        "flipped states": {
            "Florida": 722,
            "Maryland": 2473,
            "Pennsylvania": 9730,
            "North Carolina": 373,
            "Rhode Island": 555,
            "Delaware": 13,
            "Missouri": 4417,
            "Ohio": 8206,
            "Iowa": 954,
            "Louisiana": 697,
            "Connecticut": 1446
        },
        "total votes": 3159640,
        "percent votes flipped": "0.936%"
    },
    {
        "year": 1856,
        "original winner": "Buchan.",
        "new winner": "Fremont",
        "flipped votes": 26078,
        "flipped states": {
            "Illinois": 4627,
            "Indiana": 12148,
            "New Jersey": 9303
        },
        "total votes": 4051605,
        "percent votes flipped": "0.644%"
    },
    {
        "year": 1860,
        "original winner": "Lincoln",
        "new winner": "Douglas",
        "flipped votes": 56562,
        "flipped states": {
            "Rhode Island": 2269,
            "Ohio": 17195,
            "Oregon": 607,
            "Minnesota": 5075,
            "Illinois": 5979,
            "California": 368,
            "New York": 25069
        },
        "total votes": 4681267,
        "percent votes flipped": "1.208%"
    },
    {
        "year": 1864,
        "original winner": "Lincoln",
        "new winner": "McClel.",
        "flipped votes": 32733,
        "flipped states": {
            "Rhode Island": 2747,
            "Oregon": 716,
            "Pennsylvania": 10038,
            "New York": 3375,
            "New Hampshire": 1782,
            "Michigan": 5319,
            "Connecticut": 1203,
            "Maryland": 3708,
            "Minnesota": 3845
        },
        "total votes": 4018202,
        "percent votes flipped": "0.815%"
    },
    {
        "year": 1868,
        "original winner": "Grant",
        "new winner": "Seymour",
        "flipped votes": 24995,
        "flipped states": {
            "California": 261,
            "Nevada": 632,
            "Connecticut": 1473,
            "Pennsylvania": 14450,
            "Alabama": 1874,
            "Arkansas": 1518,
            "Indiana": 4787
        },
        "total votes": 5722816,
        "percent votes flipped": "0.437%"
    },
    {
        "year": 1872,
        "original winner": "Grant",
        "new winner": "Greeley",
        "flipped votes": 67037,
        "flipped states": {
            "Nevada": 1089,
            "West Virginia": 1395,
            "Florida": 1169,
            "Connecticut": 2310,
            "Alabama": 5415,
            "Indiana": 11258,
            "Delaware": 463,
            "New Hampshire": 2872,
            "Virginia": 909,
            "Wisconsin": 9259,
            "Rhode Island": 4169,
            "New York": 26729
        },
        "total votes": 6471983,
        "percent votes flipped": "1.036%"
    },
    {
        "year": 1876,
        "original winner": "Hayes",
        "new winner": "Tilden",
        "flipped votes": 445,
        "flipped states": {
            "South Carolina": 445
        },
        "total votes": 8418659,
        "percent votes flipped": "0.005%"
    },
    {
        "year": 1880,
        "original winner": "Garfie.",
        "new winner": "Hancock",
        "flipped votes": 8418,
        "flipped states": {
            "Indiana": 3322,
            "Oregon": 333,
            "Connecticut": 1331,
            "Colorado": 1402,
            "New Hampshire": 2030
        },
        "total votes": 9217410,
        "percent votes flipped": "0.091%"
    },
    {
        "year": 1884,
        "original winner": "Clevel.",
        "new winner": "Blaine",
        "flipped votes": 575,
        "flipped states": {
            "New York": 575
        },
        "total votes": 10060145,
        "percent votes flipped": "0.006%"
    },
    {
        "year": 1888,
        "original winner": "Harris.",
        "new winner": "Clevel.",
        "flipped votes": 7187,
        "flipped states": {
            "New York": 7187
        },
        "total votes": 11388846,
        "percent votes flipped": "0.063%"
    },
    {
        "year": 1892,
        "original winner": "Clevel.",
        "new winner": "Harris.",
        "flipped votes": 29093,
        "flipped states": {
            "Kansas": 2936,
            "Indiana": 3563,
            "Connecticut": 2682,
            "West Virginia": 2088,
            "Illinois": 13497,
            "Idaho": 961,
            "Delaware": 253,
            "Wisconsin": 3113
        },
        "total votes": 12068027,
        "percent votes flipped": "0.241%"
    },
    {
        "year": 1896,
        "original winner": "McKinl.",
        "new winner": "Bryan",
        "flipped votes": 39124,
        "flipped states": {
            "North Dakota": 2825,
            "Delaware": 1939,
            "Oregon": 1021,
            "Ohio": 24248,
            "Indiana": 9091
        },
        "total votes": 13938674,
        "percent votes flipped": "0.281%"
    },
    {
        "year": 1900,
        "original winner": "McKinl.",
        "new winner": "Bryan",
        "flipped votes": 73232,
        "flipped states": {
            "Kansas": 11678,
            "Utah": 1067,
            "Ohio": 34519,
            "Nebraska": 3912,
            "Indiana": 13240,
            "Maryland": 6974,
            "Delaware": 1842
        },
        "total votes": 13971846,
        "percent votes flipped": "0.524%"
    },
    {
        "year": 1904,
        "original winner": "Roosev.",
        "new winner": "Parker",
        "flipped votes": 196679,
        "flipped states": {
            "Nevada": 1442,
            "Delaware": 2180,
            "Missouri": 12569,
            "New York": 87777,
            "Rhode Island": 8384,
            "Massachusetts": 46039,
            "West Virginia": 15883,
            "New Hampshire": 10045,
            "Montana": 6580,
            "Wyoming": 5780
        },
        "total votes": 13525759,
        "percent votes flipped": "1.454%"
    },
    {
        "year": 1908,
        "original winner": "Taft",
        "new winner": "Bryan",
        "flipped votes": 77656,
        "flipped states": {
            "Montana": 1504,
            "Kansas": 18004,
            "Indiana": 5366,
            "Ohio": 34796,
            "West Virginia": 13226,
            "Missouri": 315,
            "Wyoming": 2965,
            "Delaware": 1480
        },
        "total votes": 14889109,
        "percent votes flipped": "0.522%"
    },
    {
        "year": 1912,
        "original winner": "Wilson",
        "new winner": "Roosev.",
        "flipped votes": 214209,
        "flipped states": {
            "New Hampshire": 8466,
            "New Jersey": 16440,
            "Rhode Island": 6768,
            "Kansas": 11727,
            "Idaho": 4198,
            "Arizona": 1688,
            "Wyoming": 3040,
            "North Dakota": 1915,
            "Louisiana": 25795,
            "Montana": 2743,
            "Nebraska": 18164,
            "West Virginia": 17043,
            "Maine": 1310,
            "Iowa": 11754,
            "Delaware": 6873,
            "Massachusetts": 15591,
            "Utah": 8964,
            "Vermont": 601,
            "Nevada": 1184,
            "Oregon": 4733,
            "Illinois": 9286,
            "New Mexico": 6046,
            "Alabama": 29880
        },
        "total votes": 15046540,
        "percent votes flipped": "1.424%"
    },
    {
        "year": 1916,
        "original winner": "Wilson",
        "new winner": "Hughes",
        "flipped votes": 1887,
        "flipped states": {
            "California": 1887
        },
        "total votes": 18541312,
        "percent votes flipped": "0.010%"
    },
    {
        "year": 1920,
        "original winner": "Harding",
        "new winner": "Cox",
        "flipped votes": 596492,
        "flipped states": {
            "Indiana": 92504,
            "Idaho": 21199,
            "Wyoming": 8832,
            "Delaware": 6474,
            "Connecticut": 54259,
            "New Mexico": 5484,
            "Oregon": 31787,
            "South Dakota": 37378,
            "Montana": 26030,
            "Utah": 12459,
            "New Hampshire": 16268,
            "Tennessee": 6636,
            "Missouri": 76182,
            "West Virginia": 30610,
            "Maine": 38698,
            "Arizona": 3736,
            "Nevada": 2815,
            "Oklahoma": 13390,
            "Maryland": 27746,
            "Vermont": 23647,
            "Rhode Island": 26201,
            "Colorado": 34157
        },
        "total votes": 26788225,
        "percent votes flipped": "2.227%"
    },
    {
        "year": 1924,
        "original winner": "Coolid.",
        "new winner": "Davis",
        "flipped votes": 549426,
        "flipped states": {
            "Missouri": 37867,
            "Maine": 48239,
            "South Dakota": 37043,
            "Rhode Island": 24341,
            "Maryland": 7172,
            "Utah": 15164,
            "Wyoming": 14496,
            "Delaware": 9499,
            "Arizona": 2141,
            "Nebraska": 40649,
            "Kentucky": 12056,
            "North Dakota": 40537,
            "West Virginia": 15702,
            "Indiana": 105399,
            "Idaho": 22812,
            "Vermont": 32188,
            "Oregon": 37496,
            "New Mexico": 3102,
            "New Hampshire": 20688,
            "Nevada": 2668,
            "Montana": 20167
        },
        "total votes": 29092624,
        "percent votes flipped": "1.889%"
    },
    {
        "year": 1928,
        "original winner": "Hoover",
        "new winner": "Smith",
        "flipped votes": 411248,
        "flipped states": {
            "Maryland": 38927,
            "Utah": 6817,
            "Virginia": 12232,
            "New Mexico": 10718,
            "Texas": 13003,
            "Wisconsin": 46974,
            "New York": 51741,
            "New Hampshire": 17345,
            "Missouri": 85760,
            "Arizona": 6999,
            "North Carolina": 31349,
            "Florida": 21203,
            "North Dakota": 12397,
            "Montana": 17362,
            "Tennessee": 14023,
            "Nevada": 2119,
            "Connecticut": 22279
        },
        "total votes": 36808961,
        "percent votes flipped": "1.117%"
    },
    {
        "year": 1932,
        "original winner": "Roosev.",
        "new winner": "Hoover",
        "flipped votes": 874622,
        "flipped states": {
            "Nevada": 8042,
            "New York": 298499,
            "Massachusetts": 31595,
            "Kansas": 37354,
            "Colorado": 30631,
            "Arizona": 21581,
            "New Jersey": 15474,
            "West Virginia": 37197,
            "Rhode Island": 15670,
            "South Carolina": 50185,
            "Utah": 15978,
            "Ohio": 37189,
            "Virginia": 57172,
            "Tennessee": 66361,
            "Michigan": 65904,
            "Idaho": 19032,
            "Oregon": 38927,
            "New Mexico": 20437,
            "Wyoming": 7394
        },
        "total votes": 39752454,
        "percent votes flipped": "2.200%"
    },
    {
        "year": 1936,
        "original winner": "Roosev.",
        "new winner": "Landon",
        "flipped votes": 1947814,
        "flipped states": {
            "Nevada": 10002,
            "Idaho": 29714,
            "Massachusetts": 87052,
            "Kentucky": 86122,
            "Utah": 42846,
            "Nebraska": 49858,
            "South Dakota": 17081,
            "Kansas": 33397,
            "North Dakota": 45199,
            "West Virginia": 88613,
            "Virginia": 68323,
            "Delaware": 6234,
            "Georgia": 109212,
            "Arizona": 26645,
            "South Carolina": 56073,
            "Indiana": 121703,
            "Mississippi": 76434,
            "Alabama": 101420,
            "Maryland": 79089,
            "Rhode Island": 20104,
            "Michigan": 158531,
            "Arkansas": 57364,
            "Connecticut": 51723,
            "Wyoming": 11943,
            "Pennsylvania": 331894,
            "Iowa": 66890,
            "New Hampshire": 1910,
            "New Mexico": 22156,
            "Tennessee": 90282
        },
        "total votes": 45654388,
        "percent votes flipped": "4.266%"
    },
    {
        "year": 1940,
        "original winner": "Roosev.",
        "new winner": "Willkie",
        "flipped votes": 426514,
        "flipped states": {
            "Nevada": 5359,
            "Connecticut": 27902,
            "Minnesota": 23962,
            "Delaware": 6580,
            "Missouri": 43734,
            "Ohio": 73184,
            "New Mexico": 12193,
            "Idaho": 10645,
            "New Jersey": 35667,
            "Illinois": 51348,
            "Wyoming": 3328,
            "Wisconsin": 12808,
            "New York": 112221,
            "New Hampshire": 7583
        },
        "total votes": 49912852,
        "percent votes flipped": "0.855%"
    },
    {
        "year": 1944,
        "original winner": "Roosev.",
        "new winner": "Dewey",
        "flipped votes": 278659,
        "flipped states": {
            "Nevada": 2507,
            "Connecticut": 22310,
            "Michigan": 11239,
            "Maryland": 11271,
            "Illinois": 70083,
            "Montana": 9697,
            "Missouri": 23141,
            "Idaho": 3632,
            "New Jersey": 13270,
            "New Hampshire": 4874,
            "Pennsylvania": 52713,
            "Minnesota": 31225,
            "Oregon": 11636,
            "Delaware": 5710,
            "New Mexico": 5351
        },
        "total votes": 47977092,
        "percent votes flipped": "0.581%"
    },
    {
        "year": 1948,
        "original winner": "Truman",
        "new winner": "Dewey",
        "flipped votes": 29294,
        "flipped states": {
            "Illinois": 16807,
            "California": 8933,
            "Ohio": 3554
        },
        "total votes": 48794565,
        "percent votes flipped": "0.060%"
    },
    {
        "year": 1952,
        "original winner": "Eisenh.",
        "new winner": "Steven.",
        "flipped votes": 713453,
        "flipped states": {
            "New Mexico": 13255,
            "Maryland": 52044,
            "Pennsylvania": 134761,
            "Delaware": 3373,
            "Virginia": 40181,
            "Wyoming": 16557,
            "Arizona": 21758,
            "Texas": 66826,
            "Montana": 25591,
            "Rhode Island": 3822,
            "Nevada": 9408,
            "Utah": 29414,
            "Tennessee": 1219,
            "Oklahoma": 43554,
            "Missouri": 14800,
            "Florida": 49544,
            "Washington": 53132,
            "Massachusetts": 104401,
            "New Hampshire": 29813
        },
        "total votes": 61552211,
        "percent votes flipped": "1.159%"
    },
    {
        "year": 1956,
        "original winner": "Eisenh.",
        "new winner": "Steven.",
        "flipped votes": 1141553,
        "flipped states": {
            "Wyoming": 12510,
            "New Hampshire": 43078,
            "Idaho": 30556,
            "Maryland": 93563,
            "Delaware": 9319,
            "South Dakota": 24641,
            "Michigan": 176875,
            "Arizona": 32056,
            "Texas": 110331,
            "Florida": 81740,
            "Rhode Island": 32015,
            "Oregon": 38595,
            "Washington": 48715,
            "Kentucky": 47870,
            "New Mexico": 20346,
            "Tennessee": 2891,
            "North Dakota": 30013,
            "Minnesota": 50889,
            "West Virginia": 33882,
            "Louisiana": 42536,
            "Virginia": 59350,
            "Utah": 48634,
            "Montana": 19348,
            "Oklahoma": 44095,
            "Nevada": 7705
        },
        "total votes": 62021979,
        "percent votes flipped": "1.841%"
    },
    {
        "year": 1960,
        "original winner": "Kennedy",
        "new winner": "Nixon",
        "flipped votes": 11874,
        "flipped states": {
            "Nevada": 1247,
            "New Mexico": 1148,
            "Illinois": 4430,
            "Hawaii": 58,
            "Missouri": 4991
        },
        "total votes": 68832483,
        "percent votes flipped": "0.017%"
    },
    {
        "year": 1964,
        "original winner": "Johnson",
        "new winner": "Goldwa.",
        "flipped votes": 2059257,
        "flipped states": {
            "Montana": 25608,
            "Tennessee": 62992,
            "Florida": 21300,
            "New Hampshire": 40018,
            "Nebraska": 15231,
            "Delaware": 22314,
            "Texas": 352310,
            "New Mexico": 31090,
            "Indiana": 129866,
            "Iowa": 141942,
            "Virginia": 38353,
            "Arkansas": 35467,
            "North Dakota": 20789,
            "Alaska": 10700,
            "Kansas": 38725,
            "Wyoming": 9361,
            "Nevada": 11623,
            "Oregon": 109120,
            "South Dakota": 16452,
            "Vermont": 26593,
            "North Carolina": 87648,
            "Utah": 19474,
            "California": 646385,
            "Oklahoma": 53585,
            "Colorado": 89629,
            "Idaho": 2682
        },
        "total votes": 70641539,
        "percent votes flipped": "2.915%"
    },
    {
        "year": 1968,
        "original winner": "Nixon",
        "new winner": "Humphr.",
        "flipped votes": 135284,
        "flipped states": {
            "Nevada": 6296,
            "Alaska": 1095,
            "Delaware": 3761,
            "Missouri": 10245,
            "Wisconsin": 30597,
            "New Jersey": 30631,
            "Vermont": 7444,
            "Ohio": 45215
        },
        "total votes": 73199999,
        "percent votes flipped": "0.185%"
    },
    {
        "year": 1972,
        "original winner": "Nixon",
        "new winner": "McGove.",
        "flipped votes": 3174786,
        "flipped states": {
            "Delaware": 24038,
            "Iowa": 105001,
            "Oregon": 46964,
            "California": 563125,
            "South Dakota": 13266,
            "Wyoming": 28054,
            "South Carolina": 144579,
            "New York": 620848,
            "Maine": 47938,
            "Illinois": 437354,
            "Minnesota": 47962,
            "Maryland": 161763,
            "Vermont": 24488,
            "Hawaii": 33729,
            "New Hampshire": 48645,
            "New Mexico": 47262,
            "Wisconsin": 89629,
            "Washington": 134401,
            "Nevada": 24868,
            "Connecticut": 127633,
            "North Dakota": 36863,
            "Rhode Island": 12870,
            "Montana": 31890,
            "Idaho": 59280,
            "Alaska": 11192,
            "Michigan": 251144
        },
        "total votes": 77744030,
        "percent votes flipped": "4.084%"
    },
    {
        "year": 1976,
        "original winner": "Carter",
        "new winner": "Ford",
        "flipped votes": 9246,
        "flipped states": {
            "Ohio": 5559,
            "Hawaii": 3687
        },
        "total votes": 81540780,
        "percent votes flipped": "0.011%"
    },
    {
        "year": 1980,
        "original winner": "Reagan",
        "new winner": "Carter",
        "flipped votes": 731189,
        "flipped states": {
            "Pennsylvania": 162167,
            "Mississippi": 5905,
            "Illinois": 188319,
            "Wisconsin": 53631,
            "Tennessee": 2356,
            "Michigan": 126847,
            "Vermont": 6354,
            "Arkansas": 2562,
            "New York": 82730,
            "Louisiana": 42201,
            "North Carolina": 19692,
            "Delaware": 2750,
            "Kentucky": 9429,
            "Alabama": 8732,
            "Maine": 8775,
            "South Carolina": 6824,
            "Massachusetts": 1915
        },
        "total votes": 86509678,
        "percent votes flipped": "0.845%"
    },
    {
        "year": 1984,
        "original winner": "Reagan",
        "new winner": "Mondale",
        "flipped votes": 2675811,
        "flipped states": {
            "Maine": 60993,
            "Vermont": 20068,
            "Pennsylvania": 178097,
            "California": 772246,
            "Rhode Island": 7488,
            "Georgia": 181048,
            "West Virginia": 38680,
            "New Mexico": 52667,
            "Massachusetts": 35666,
            "Washington": 122160,
            "Iowa": 48735,
            "Maryland": 45992,
            "Nevada": 48558,
            "Hawaii": 18949,
            "Wisconsin": 101477,
            "Delaware": 25268,
            "New York": 272578,
            "Montana": 42855,
            "Wyoming": 39936,
            "Tennessee": 139250,
            "Alaska": 38186,
            "Illinois": 310303,
            "Oregon": 74611
        },
        "total votes": 92653233,
        "percent votes flipped": "2.888%"
    },
    {
        "year": 1988,
        "original winner": "Bush",
        "new winner": "Dukakis",
        "flipped votes": 537766,
        "flipped states": {
            "Connecticut": 36829,
            "Vermont": 4279,
            "Delaware": 15497,
            "New Mexico": 12923,
            "Missouri": 41668,
            "Colorado": 53363,
            "North Dakota": 19411,
            "Maine": 31782,
            "South Dakota": 9928,
            "Maryland": 24932,
            "Pennsylvania": 52572,
            "California": 176343,
            "Illinois": 47500,
            "Montana": 10739
        },
        "total votes": 91594686,
        "percent votes flipped": "0.587%"
    },
    {
        "year": 1992,
        "original winner": "Clinton",
        "new winner": "Bush",
        "flipped votes": 284837,
        "flipped states": {
            "Georgia": 6858,
            "Kentucky": 23964,
            "Louisiana": 41293,
            "Ohio": 45317,
            "Delaware": 11871,
            "New Hampshire": 3279,
            "Montana": 5151,
            "Colorado": 33416,
            "Nevada": 6661,
            "Tennessee": 46111,
            "New Jersey": 39671,
            "Hawaii": 21245
        },
        "total votes": 104426611,
        "percent votes flipped": "0.273%"
    },
    {
        "year": 1996,
        "original winner": "Clinton",
        "new winner": "Dole",
        "flipped votes": 575515,
        "flipped states": {
            "Tennessee": 22809,
            "Oregon": 55745,
            "Florida": 151168,
            "Ohio": 144170,
            "New Hampshire": 24842,
            "Kentucky": 6666,
            "Iowa": 63808,
            "New Mexico": 20373,
            "Nevada": 2366,
            "Arizona": 15608,
            "Missouri": 67960
        },
        "total votes": 96275640,
        "percent votes flipped": "0.598%"
    },
    {
        "year": 2000,
        "original winner": "Bush",
        "new winner": "Gore",
        "flipped votes": 269,
        "flipped states": {
            "Florida": 269
        },
        "total votes": 105425985,
        "percent votes flipped": "0.00026%"
    },
    {
        "year": 2004,
        "original winner": "Bush",
        "new winner": "Kerry",
        "flipped votes": 57791,
        "flipped states": {
            "New Mexico": 2995,
            "Colorado": 49766,
            "Iowa": 5030
        },
        "total votes": 122303590,
        "percent votes flipped": "0.047%"
    },
    {
        "year": 2008,
        "original winner": "Obama",
        "new winner": "McCain",
        "flipped votes": 495165,
        "flipped states": {
            "New Hampshire": 34147,
            "Virginia": 117264,
            "Iowa": 73281,
            "Indiana": 14196,
            "North Carolina": 7089,
            "Florida": 118075,
            "Ohio": 131113
        },
        "total votes": 131473705,
        "percent votes flipped": "0.377%"
    },
    {
        "year": 2012,
        "original winner": "Obama",
        "new winner": "Romney",
        "flipped votes": 214764,
        "flipped states": {
            "Florida": 37155,
            "Virginia": 74650,
            "Ohio": 83137,
            "New Hampshire": 19822
        },
        "total votes": 129237642,
        "percent votes flipped": "0.166%"
    },
    {
        "year": 2016,
        "original winner": "Trump",
        "new winner": "Clinton",
        "flipped votes": 38871,
        "flipped states": {
            "Wisconsin": 11375,
            "Michigan": 5353,
            "Pennsylvania": 22143
        },
        "total votes": 137143218,
        "percent votes flipped": "0.028%"
    },
    {
        "year": 2020,
        "original winner": "Biden",
        "new winner": "Trump",
        "flipped votes": 38260,
        "flipped states": {
            "Arizona": 5229,
            "Nevada": 16799,
            "Wisconsin": 10342,
            "Georgia": 5890
        },
        "total votes": 158590894,
        "percent votes flipped": "0.024%"
    }
]